{"schemaVersion":"1.0","appDefinitionTemplate":{"id":"/providers/Microsoft.PowerApps/apps/","type":"Microsoft.PowerApps/apps","tags":{"sp-site-id":"https://acadkroton.sharepoint.com/sites/Compliance","sp-list-id":"8cb8154f-a42e-4c4d-b23b-94b3eba14791","https://acadkroton.sharepoint.com/sites/Compliance":"8cb8154f-a42e-4c4d-b23b-94b3eba14791","primaryDeviceWidth":"640","primaryDeviceHeight":"1136","sienaVersion":"20210828T014722Z-3.21083.27.0","deviceCapabilities":"","supportsPortrait":"true","supportsLandscape":"true","primaryFormFactor":"Phone","publisherVersion":"3.21083.28","minimumRequiredApiVersion":"2.2.0","hasComponent":"false","hasUnlockedComponent":"false","isUnifiedRootApp":"false"},"properties":{"appVersion":"2021-08-28T01:47:22Z","lifeCycleId":"Published","createdByClientVersion":{"major":3,"minor":21083,"build":28,"revision":0,"majorRevision":0,"minorRevision":0},"minClientVersion":{"major":3,"minor":21083,"build":28,"revision":0,"majorRevision":0,"minorRevision":0},"backgroundColor":"rgba(0, 176, 240, 1)","backgroundImageUri":"/17041076607053931008/N2b04aff4-d6d2-4e89-8cf5-acbe2576548d-logoSmallFile","displayName":"COI PowerA","description":"","commitMessage":"test 1.3","appUris":{"documentUri":{"value":"/17041076607053931008/Nd3937145-3953-49c7-aaef-9f797502f010-document.msapp"},"imageUris":[]},"createdTime":"0001-01-01T00:00:00Z","lastModifiedTime":"0001-01-01T00:00:00Z","sharedGroupsCount":0,"sharedUsersCount":0,"icons":{"smallIconUri":"/17041076607053931008/N0bc07482-456a-4af2-addf-1ca11a2566a5-small.png","mediumIconUri":"/17041076607053931008/N5212a1c4-f0d2-4f1a-bb3a-c4bd584d0df0-medium.png","largeIconUri":"/17041076607053931008/N3c97b3ea-3f5d-4340-8cbe-a0351d3ee512-large.png","wideIconUri":"/17041076607053931008/Nff6f47c5-afa1-474f-9e1c-7a815e5c1826-wide.png"},"connectionReferences":{"7c240136-82f6-4942-94ca-678e382767d7":{"id":"d93f48d6-bf6d-4634-9054-34aa7d0e06d0","displayName":"SharePoint","iconUri":"https://connectoricons-prod.azureedge.net/releases/v1.0.1505/1.0.1505.2520/sharepointonline/icon.png","dataSources":["Comflito de interesses"],"dependencies":[],"dependents":[],"parameterHints":{},"parameterHintsV2":{},"isOnPremiseConnection":false,"bypassConsent":false,"dataSets":{"https://acadkroton.sharepoint.com/sites/Compliance":{"dataSources":{"Comflito de interesses":{"tableName":"8cb8154f-a42e-4c4d-b23b-94b3eba14791"}}}},"apiTier":"Standard","isCustomApiConnection":false,"actions":["providers/PowerPlatform.Governance/Operations/Read","providers/PowerPlatform.Governance/Operations/Write","providers/PowerPlatform.Governance/Operations/Delete"]}},"databaseReferences":{},"almMode":"Environment","performanceOptimizationEnabled":true,"canConsumeAppPass":true,"executionRestrictions":{"isTeamsOnly":false,"dataLossPreventionEvaluationResult":{"status":"Compliant","lastEvaluationDate":"2021-08-27T23:58:08.7328409Z","violations":[],"violationsByPolicy":[],"violationErrorMessage":"O aplicativo usa os seguintes conectores: shared_sharepointonline."}}},"appType":"ClassicCanvasApp","appComponents":[]}}